{
  "experiment_name": "graded_betrayal_precision_mod_full",
  "payoff_mode": "graded",
  "num_investment_levels": 6,
  "endowment": 10.0,
  "multiplier": 3.0,
  "num_partners": 4,
  "num_rounds": 120,
  "p_switch": 0.0,
  "assignment_mode": "agent_choice",
  "observation_noise": 0.0,
  "correlation_pairs": [],
  "correlation_strength": 0.9,
  "initial_partner_types": ["cooperator", "reciprocator", "cooperator", "random"],
  "initial_partner_stances": ["trusting", "neutral", "neutral", "neutral"],
  "scheduled_stance_switches": [
    {"round": 31, "partner_idx": 0, "to_stance": "hostile"}
  ],
  "gamma": 1.0,
  "lr": 0.1,
  "action_sampling": "marginal",
  "affect_modulates_precision": true,
  "use_parameter_learning": false,
  "deep_horizon": 8,
  "shallow_horizon": 2,
  "max_policies": 4096,
  "lambda_smooth": 0.6,
  "alpha_charge": 3.0,
  "sigma_0_sq": 0.25,
  "mu": null,
  "initial_beta": 0.5,
  "lesion_mode": "decouple",
  "num_replications": 50,
  "calibration_episodes": 5,
  "random_seed": 42,
  "conditions": [5, 6],
  "presets": ["reward_average"],
  "partner_types": ["cooperator", "reciprocator", "exploiter", "random"],
  "run_sensitivity": false
}
